LICENSE
colour_workbench/ETC/__init__.py
colour_workbench/ETC/analysis.py
colour_workbench/ETC/fonts/Anuphan/Anuphan.ttf
colour_workbench/ETC/fonts/Anuphan/OFL.txt
colour_workbench/ETC/fonts/Anuphan/README.txt
colour_workbench/ETC/fonts/Anuphan/__init__.py
colour_workbench/ETC/fonts/__init__.py
colour_workbench/ETC/pdf.py
colour_workbench/ETC/readme.ipynb
colour_workbench/__init__.py
colour_workbench/measurement_controllers.py
colour_workbench/scripts/__init__.py
colour_workbench/scripts/analyze_display_measurements.py
colour_workbench/scripts/measure_display.py
colour_workbench/test_colors.py
colour_workbench/tpg_controller.py
colour_workbench/utilities.py
colour_workbench-0.1.1.dist-info/LICENSE
colour_workbench-0.1.1.dist-info/METADATA
colour_workbench-0.1.1.dist-info/WHEEL
colour_workbench-0.1.1.dist-info/RECORD
